Workbook
Name Slicer_Category: #N/A
Name Slicer_Months__Date: #N/A

Sheet products
A1: Product | B1: Price | C1: Cost
A2: Monk Straps | B2: 89 | C2: 47
A3: Loafers | B3: 54 | C3: 28
A4: Derby | B4: 32 | C4: 14
A5: Boots | B5: 76 | C5: 39
A6: Canvas | B6: 128 | C6: 72
A7: Oxford | B7: 105 | C7: 58
A8: Brogues | B8: 112 | C8: 64
A9: Slippers | B9: 119 | C9: 67

Sheet shoe_sales_clean_data
A1: ID | B1: Date | C1: Product | D1: Category | E1: Color | F1: Brand | G1: Country | H1: Quantity | I1: Payment Type | J1: Cost Price | K1: Selling Price | L1: Cost | M1: Revenue | N1: Profit | O1: Profit Margin
A2: T001 | B2: 46023 | C2: Slippers | D2: Casual | E2: Black | F2: Clarks | G2: USA | H2: 9 | I2: Cash | J2: =VLOOKUP(Shoe_Sales[[#This Row],[Product]],products!$A$1:$C$9,3,0) -> 67 | K2: =VLOOKUP(Shoe_Sales[[#This Row],[Product]],products!$A$1:$C$9,2,FALSE) -> 119 | L2: =Shoe_Sales[[#This Row],[Cost Price]]*Shoe_Sales[[#This Row],[Quantity]] -> 603 | M2: =Shoe_Sales[[#This Row],[Selling Price]]*Shoe_Sales[[#This Row],[Quantity]] -> 1071 | N2: =Shoe_Sales[[#This Row],[Revenue]]-Shoe_Sales[[#This Row],[Cost]] -> 468 | O2: =Shoe_Sales[[#This Row],[Profit]]/Shoe_Sales[[#This Row],[Revenue]] -> 0.43697479
A3: T002 | B3: 46023 | C3: Boots | D3: Casual | E3: Red | F3: Clarks | G3: India | H3: 12 | I3: Cash | J3: =VLOOKUP(Shoe_Sales[[#This Row],[Product]],products!$A$1:$C$9,3,0) -> 39 | K3: =VLOOKUP(Shoe_Sales[[#This Row],[Product]],products!$A$1:$C$9,2,FALSE) -> 76 | L3: =Shoe_Sales[[#This Row],[Cost Price]]*Shoe_Sales[[#This Row],[Quantity]] -> 468 | M3: =Shoe_Sales[[#This Row],[Selling Price]]*Shoe_Sales[[#This Row],[Quantity]] -> 912 | N3: =Shoe_Sales[[#This Row],[Revenue]]-Shoe_Sales[[#This Row],[Cost]] -> 444 | O3: =Shoe_Sales[[#This Row],[Profit]]/Shoe_Sales[[#This Row],[Revenue]] -> 0.48684211
A4: T003 | B4: 46024 | C4: Boots | D4: Formal | E4: Black | F4: Clarks | G4: Canada | H4: 11 | I4: Card | J4: =VLOOKUP(Shoe_Sales[[#This Row],[Product]],products!$A$1:$C$9,3,0) -> 39 | K4: =VLOOKUP(Shoe_Sales[[#This Row],[Product]],products!$A$1:$C$9,2,FALSE) -> 76 | L4: =Shoe_Sales[[#This Row],[Cost Price]]*Shoe_Sales[[#This Row],[Quantity]] -> 429 | M4: =Shoe_Sales[[#This Row],[Selling Price]]*Shoe_Sales[[#This Row],[Quantity]] -> 836 | N4: =Shoe_Sales[[#This Row],[Revenue]]-Shoe_Sales[[#This Row],[Cost]] -> 407 | O4: =Shoe_Sales[[#This Row],[Profit]]/Shoe_Sales[[#This Row],[Revenue]] -> 0.48684211
A5: T004 | B5: 46024 | C5: Loafers | D5: Formal | E5: Black | F5: Steve Madden | G5: Cyprus | H5: 13 | I5: Mobile Money | J5: =VLOOKUP(Shoe_Sales[[#This Row],[Product]],products!$A$1:$C$9,3,0) -> 28 | K5: =VLOOKUP(Shoe_Sales[[#This Row],[Product]],products!$A$1:$C$9,2,FALSE) -> 54 | L5: =Shoe_Sales[[#This Row],[Cost Price]]*Shoe_Sales[[#This Row],[Quantity]] -> 364 | M5: =Shoe_Sales[[#This Row],[Selling Price]]*Shoe_Sales[[#This Row],[Quantity]] -> 702 | N5: =Shoe_Sales[[#This Row],[Revenue]]-Shoe_Sales[[#This Row],[Cost]] -> 338 | O5: =Shoe_Sales[[#This Row],[Profit]]/Shoe_Sales[[#This Row],[Revenue]] -> 0.48148148
A6: T005 | B6: 46024 | C6: Monk Straps | D6: Utility | E6: Blue | F6: Zara | G6: Nigeria | H6: 12 | I6: Cash | J6: =VLOOKUP(Shoe_Sales[[#This Row],[Product]],products!$A$1:$C$9,3,0) -> 47 | K6: =VLOOKUP(Shoe_Sales[[#This Row],[Product]],products!$A$1:$C$9,2,FALSE) -> 89 | L6: =Shoe_Sales[[#This Row],[Cost Price]]*Shoe_Sales[[#This Row],[Quantity]] -> 564 | M6: =Shoe_Sales[[#This Row],[Selling Price]]*Shoe_Sales[[#This Row],[Quantity]] -> 1068 | N6: =Shoe_Sales[[#This Row],[Revenue]]-Shoe_Sales[[#This Row],[Cost]] -> 504 | O6: =Shoe_Sales[[#This Row],[Profit]]/Shoe_Sales[[#This Row],[Revenue]] -> 0.47191011
A7: T006 | B7: 46025 | C7: Derby | D7: Formal | E7: Red | F7: Clarks | G7: Philippines | H7: 15 | I7: Mobile Money | J7: =VLOOKUP(Shoe_Sales[[#This Row],[Product]],products!$A$1:$C$9,3,0) -> 14 | K7: =VLOOKUP(Shoe_Sales[[#This Row],[Product]],products!$A$1:$C$9,2,FALSE) -> 32 | L7: =Shoe_Sales[[#This Row],[Cost Price]]*Shoe_Sales[[#This Row],[Quantity]] -> 210 | M7: =Shoe_Sales[[#This Row],[Selling Price]]*Shoe_Sales[[#This Row],[Quantity]] -> 480 | N7: =Shoe_Sales[[#This Row],[Revenue]]-Shoe_Sales[[#This Row],[Cost]] -> 270 | O7: =Shoe_Sales[[#This Row],[Profit]]/Shoe_Sales[[#This Row],[Revenue]] -> 0.5625
A8: T007 | B8: 46025 | C8: Boots | D8: Formal | E8: Blue | F8: Clarks | G8: USA | H8: 13 | I8: Card | J8: =VLOOKUP(Shoe_Sales[[#This Row],[Product]],products!$A$1:$C$9,3,0) -> 39 | K8: =VLOOKUP(Shoe_Sales[[#This Row],[Product]],products!$A$1:$C$9,2,FALSE) -> 76 | L8: =Shoe_Sales[[#This Row],[Cost Price]]*Shoe_Sales[[#This Row],[Quantity]] -> 507 | M8: =Shoe_Sales[[#This Row],[Selling Price]]*Shoe_Sales[[#This Row],[Quantity]] -> 988 | N8: =Shoe_Sales[[#This Row],[Revenue]]-Shoe_Sales[[#This Row],[Cost]] -> 481 | O8: =Shoe_Sales[[#This Row],[Profit]]/Shoe_Sales[[#This Row],[Revenue]] -> 0.48684211
A9: T008 | B9: 46025 | C9: Loafers | D9: Casual | E9: Blue | F9: Clarks | G9: Uganda | H9: 14 | I9: Cash | J9: =VLOOKUP(Shoe_Sales[[#This Row],[Product]],products!$A$1:$C$9,3,0) -> 28 | K9: =VLOOKUP(Shoe_Sales[[#This Row],[Product]],products!$A$1:$C$9,2,FALSE) -> 54 | L9: =Shoe_Sales[[#This Row],[Cost Price]]*Shoe_Sales[[#This Row],[Quantity]] -> 392 | M9: =Shoe_Sales[[#This Row],[Selling Price]]*Shoe_Sales[[#This Row],[Quantity]] -> 756 | N9: =Shoe_Sales[[#This Row],[Revenue]]-Shoe_Sales[[#This Row],[Cost]] -> 364 | O9: =Shoe_Sales[[#This Row],[Profit]]/Shoe_Sales[[#This Row],[Revenue]] -> 0.48148148
A10: T009 | B10: 46026 | C10: Slippers | D10: Casual | E10: Green | F10: Clarks | G10: Zimbabwe | H10: 9 | I10: Card | J10: =VLOOKUP(Shoe_Sales[[#This Row],[Product]],products!$A$1:$C$9,3,0) -> 67 | K10: =VLOOKUP(Shoe_Sales[[#This Row],[Product]],products!$A$1:$C$9,2,FALSE) -> 119 | L10: =Shoe_Sales[[#This Row],[Cost Price]]*Shoe_Sales[[#This Row],[Quantity]] -> 603 | M10: =Shoe_Sales[[#This Row],[Selling Price]]*Shoe_Sales[[#This Row],[Quantity]] -> 1071 | N10: =Shoe_Sales[[#This Row],[Revenue]]-Shoe_Sales[[#This Row],[Cost]] -> 468 | O10: =Shoe_Sales[[#This Row],[Profit]]/Shoe_Sales[[#This Row],[Revenue]] -> 0.43697479
A11: T010 | B11: 46026 | C11: Oxford | D11: Casual | E11: Brown | F11: Timberland | G11: India | H11: 3 | I11: Mobile Money | J11: =VLOOKUP(Shoe_Sales[[#This Row],[Product]],products!$A$1:$C$9,3,0) -> 58 | K11: =VLOOKUP(Shoe_Sales[[#This Row],[Product]],products!$A$1:$C$9,2,FALSE) -> 105 | L11: =Shoe_Sales[[#This Row],[Cost Price]]*Shoe_Sales[[#This Row],[Quantity]] -> 174 | M11: =Shoe_Sales[[#This Row],[Selling Price]]*Shoe_Sales[[#This Row],[Quantity]] -> 315 | N11: =Shoe_Sales[[#This Row],[Revenue]]-Shoe_Sales[[#This Row],[Cost]] -> 141 | O11: =Shoe_Sales[[#This Row],[Profit]]/Shoe_Sales[[#This Row],[Revenue]] -> 0.44761905
A12: T011 | B12: 46028 | C12: Oxford | D12: Formal | E12: Red | F12: Nike | G12: Ghana | H12: 9 | I12: Bank Transfer | J12: =VLOOKUP(Shoe_Sales[[#This Row],[Product]],products!$A$1:$C$9,3,0) -> 58 | K12: =VLOOKUP(Shoe_Sales[[#This Row],[Product]],products!$A$1:$C$9,2,FALSE) -> 105 | L12: =Shoe_Sales[[#This Row],[Cost Price]]*Shoe_Sales[[#This Row],[Quantity]] -> 522 | M12: =Shoe_Sales[[#This Row],[Selling Price]]*Shoe_Sales[[#This Row],[Quantity]] -> 945 | N12: =Shoe_Sales[[#This Row],[Revenue]]-Shoe_Sales[[#This Row],[Cost]] -> 423 | O12: =Shoe_Sales[[#This Row],[Profit]]/Shoe_Sales[[#This Row],[Revenue]] -> 0.44761905
A13: T012 | B13: 46028 | C13: Boots | D13: Casual | E13: Blue | F13: Steve Madden | G13: Nigeria | H13: 1 | I13: Bank Transfer | J13: =VLOOKUP(Shoe_Sales[[#This Row],[Product]],products!$A$1:$C$9,3,0) -> 39 | K13: =VLOOKUP(Shoe_Sales[[#This Row],[Product]],products!$A$1:$C$9,2,FALSE) -> 76 | L13: =Shoe_Sales[[#This Row],[Cost Price]]*Shoe_Sales[[#This Row],[Quantity]] -> 39 | M13: =Shoe_Sales[[#This Row],[Selling Price]]*Shoe_Sales[[#This Row],[Quantity]] -> 76 | N13: =Shoe_Sales[[#This Row],[Revenue]]-Shoe_Sales[[#This Row],[Cost]] -> 37 | O13: =Shoe_Sales[[#This Row],[Profit]]/Shoe_Sales[[#This Row],[Revenue]] -> 0.48684211
... A501: T500 | B501: 46248 | C501: Monk Straps | D501: Formal | E501: Green | F501: Zara | G501: USA | H501: 5 | I501: Mobile Money | J501: =VLOOKUP(Shoe_Sales[[#This Row],[Product]],products!$A$1:$C$9,3,0) -> 47 | K501: =VLOOKUP(Shoe_Sales[[#This Row],[Product]],products!$A$1:$C$9,2,FALSE) -> 89 | L501: =Shoe_Sales[[#This Row],[Cost Price]]*Shoe_Sales[[#This Row],[Quantity]] -> 235 | M501: =Shoe_Sales[[#This Row],[Selling Price]]*Shoe_Sales[[#This Row],[Quantity]] -> 445 | N501: =Shoe_Sales[[#This Row],[Revenue]]-Shoe_Sales[[#This Row],[Cost]] -> 210 | O501: =Shoe_Sales[[#This Row],[Profit]]/Shoe_Sales[[#This Row],[Revenue]] -> 0.47191011

Sheet Sheet3
A3: Product | B3: Revenue
A4: Derby | B4: 16704
A5: Loafers | B5: 24462
A6: Slippers | B6: 40698
A7: Boots | B7: 41040
A8: Monk Straps | B8: 51175
A9: Brogues | B9: 58576
A10: Oxford | B10: 58905
A11: Canvas | B11: 63488
A12: Grand Total | B12: 355048

Sheet Analysis
A2: 1 | B2: Overall Performance | I2: 2 | J2: Revenue & Profit over time | S2: 3 | T2: Products driving sales | AF2: 4 | AG2: Profitability by Product | AS2: 5 | AT2: Revenue by Brand | BC2: 5 | BD2: Revenue by Category | BM2: 6 | BN2: Countries driving Revenue | BV2: 7 | BW2: Product Purchasing Pattern by Payment Method
B3: Transactions | C3: Revenue | D3: Profit | E3: Quantity Sold | F3: Profit Margin % | J3: Month | K3: Revenue | L3: Profit | T3: Product | U3: Revenue | V3: Qty Sold | AG3: Product | AH3: Profit | AI3: % Profit Margin | AT3: Brand | AU3: Revenue | AV3: Profit | BD3: Brand | BE3: Revenue | BN3: Country | BO3: Revenue | BP3: Profit | BW3: Transactions | BX3: Payment Method
B4: 500 | C4: 355048 | D4: 162335 | E4: 4012 | F4: 0.45721987 | J4: Jan | K4: 43801 | L4: 20299 | T4: Canvas | U4: 63488 | V4: 496 | AG4: Canvas | AH4: 27776 | AI4: 0.4375 | AT4: Clarks | AU4: 123543 | AV4: 56574 | BD4: Formal | BE4: 179935 | BN4: USA | BO4: 39127 | BP4: 17892 | BW4: Product | BX4: Card | BY4: Bank Transfer | BZ4: Cash | CA4: Mobile Money | CB4: Grand Total
J5: Feb | K5: 40664 | L5: 18698 | T5: Oxford | U5: 58905 | V5: 561 | AG5: Oxford | AH5: 26367 | AI5: 0.44761905 | AT5: Zara | AU5: 94797 | AV5: 43424 | BD5: Casual | BE5: 82917 | BN5: UK | BO5: 32871 | BP5: 15393 | BW5: Canvas | BX5: 13 | BY5: 23 | BZ5: 17 | CA5: 8 | CB5: 61
J6: Mar | K6: 45492 | L6: 20869 | T6: Brogues | U6: 58576 | V6: 523 | AG6: Brogues | AH6: 25104 | AI6: 0.42857143 | AT6: Nike | AU6: 54029 | AV6: 24513 | BD6: Open | BE6: 53035 | BN6: Ghana | BO6: 32026 | BP6: 14468 | BW6: Boots | BX6: 20 | BY6: 21 | BZ6: 12 | CA6: 18 | CB6: 71
J7: Apr | K7: 44204 | L7: 20067 | T7: Monk Straps | U7: 51175 | V7: 575 | AG7: Monk Straps | AH7: 24150 | AI7: 0.47191011 | AT7: Steve Madden | AU7: 43855 | AV7: 19932 | BD7: Utility | BE7: 39161 | BN7: Zimbabwe | BO7: 30124 | BP7: 13584 | BW7: Brogues | BX7: 15 | BY7: 18 | BZ7: 15 | CA7: 15 | CB7: 63
J8: May | K8: 44578 | L8: 20407 | T8: Boots | U8: 41040 | V8: 540 | AG8: Boots | AH8: 19980 | AI8: 0.48684211 | AT8: Timberland | AU8: 38824 | AV8: 17892 | BD8: Grand Total | BE8: 355048 | BN8: India | BO8: 29392 | BP8: 13441 | BW8: Loafers | BX8: 14 | BY8: 17 | BZ8: 13 | CA8: 12 | CB8: 56
J9: Jun | K9: 70771 | L9: 32123 | T9: Slippers | U9: 40698 | V9: 342 | AG9: Slippers | AH9: 17784 | AI9: 0.43697479 | AT9: Grand Total | AU9: 355048 | AV9: 162335 | BN9: Grand Total | BO9: 163540 | BP9: 74778 | BW9: Monk Straps | BX9: 18 | BY9: 16 | BZ9: 21 | CA9: 14 | CB9: 69
J10: Jul | K10: 49497 | L10: 22517 | T10: Loafers | U10: 24462 | V10: 453 | AG10: Loafers | AH10: 11778 | AI10: 0.48148148 | BW10: Oxford | BX10: 19 | BY10: 15 | BZ10: 16 | CA10: 12 | CB10: 62
J11: Aug | K11: 16041 | L11: 7355 | T11: Derby | U11: 16704 | V11: 522 | AG11: Derby | AH11: 9396 | AI11: 0.5625 | AT11: =AT4 -> Clarks | AU11: =GETPIVOTDATA("Revenue ",$AT$3,"Brand","Clarks")/GETPIVOTDATA("Revenue ",$AT$3) -> 0.3479614 | BW11: Derby | BX11: 20 | BY11: 14 | BZ11: 18 | CA11: 14 | CB11: 66
J12: Grand Total | K12: 355048 | L12: 162335 | T12: Grand Total | U12: 355048 | V12: 4012 | AG12: Grand Total | AH12: 162335 | AI12: 0.45721987 | AT12: =AT5 -> Zara | AU12: =GETPIVOTDATA("Revenue ",$AT$3,"Brand","Zara")/GETPIVOTDATA("Revenue ",$AT$3) -> 0.2669977 | BW12: Slippers | BX12: 18 | BY12: 11 | BZ12: 13 | CA12: 10 | CB12: 52
AU13: =SUM(AU11:AU12) -> 0.6149591 | BW13: Grand Total | BX13: 137 | BY13: 135 | BZ13: 125 | CA13: 103 | CB13: 500
T14: Contributions to Revenue | AG14: Top 3 Contributors
T15: =T4 -> Canvas | U15: =U4/GETPIVOTDATA("Revenue ",$T$3) -> 0.17881526 | AG15: =AG4 -> Canvas | AH15: =GETPIVOTDATA("Profit ",$AG$3,"Product","Canvas")/GETPIVOTDATA("Profit ",$AG$3) -> 0.17110297
T16: =T5 -> Oxford | U16: =U5/GETPIVOTDATA("Revenue ",$T$3) -> 0.16590714 | AG16: =AG5 -> Oxford | AH16: =GETPIVOTDATA("Profit ",$AG$3,"Product","Oxford")/GETPIVOTDATA("Profit ",$AG$3) -> 0.16242338
T17: =T6 -> Brogues | U17: =U6/GETPIVOTDATA("Revenue ",$T$3) -> 0.16498051 | AG17: =AG6 -> Brogues | AH17: =GETPIVOTDATA("Profit ",$AG$3,"Product","Brogues")/GETPIVOTDATA("Profit ",$AG$3) -> 0.15464318
U18: =SUM(U15:U17) -> 0.50970291 | AH18: =SUM(AH15:AH17) -> 0.48816953
BN25: Combined contribution | BO25: =GETPIVOTDATA("Revenue ",$BN$3)/GETPIVOTDATA("Revenue",$BD$3) -> 0.46061378

Sheet Dashboard
